[
  {
    "document": "chapter1.txt",
    "version_change": "chapter1_0 to chapter1_1",
    "status": "unchanged",
    "changed_date": "2025-11-07",
    "changed_time": "11:30:51",
    "page_number": "",
    "line_number": "",
    "description": "No change detected",
    "lines_added_count": 0,
    "lines_removed_count": 0,
    "lines_added_text": "",
    "lines_removed_text": ""
  },
  {
    "document": "chapter1.txt",
    "version_change": "chapter1_1 to chapter1_2",
    "status": "unchanged",
    "changed_date": "2025-11-07",
    "changed_time": "11:30:51",
    "page_number": "",
    "line_number": "",
    "description": "No change detected",
    "lines_added_count": 0,
    "lines_removed_count": 0,
    "lines_added_text": "",
    "lines_removed_text": ""
  },
  {
    "document": "chapter2.txt",
    "version_change": "chapter2_0 to chapter2_1",
    "status": "changed",
    "changed_date": "2025-11-07",
    "changed_time": "14:43:49",
    "page_number": 1,
    "line_number": 3,
    "description": "Word changed",
    "lines_added_count": 1,
    "lines_removed_count": 1,
    "lines_added_text": "The doors, normally open, were sealed by the High Council’s seal—a wax impression that shimmered faintly with protective wards.",
    "lines_removed_text": "The doors, normally open, were sealed by the Council’s sigil—a wax impression that shimmered faintly with protective wards."
  },
  {
    "document": "chapter2.txt",
    "version_change": "chapter2_0 to chapter2_1",
    "status": "changed",
    "changed_date": "2025-11-07",
    "changed_time": "14:43:49",
    "page_number": 1,
    "line_number": 6,
    "description": "Word changed",
    "lines_added_count": 1,
    "lines_removed_count": 1,
    "lines_added_text": "A faint hum of magic lingered in the air, uneasy and new.",
    "lines_removed_text": "Her assistant, Leron, appeared from behind a stack of crates, his face pale."
  },
  {
    "document": "chapter2.txt",
    "version_change": "chapter2_0 to chapter2_1",
    "status": "changed",
    "changed_date": "2025-11-07",
    "changed_time": "14:43:49",
    "page_number": 1,
    "line_number": 8,
    "description": "Word changed",
    "lines_added_count": 1,
    "lines_removed_count": 1,
    "lines_added_text": "Together they entered the Archive Hall.",
    "lines_removed_text": "She nodded."
  },
  {
    "document": "chapter2.txt",
    "version_change": "chapter2_1 to chapter2_2",
    "status": "unchanged",
    "changed_date": "2025-11-07",
    "changed_time": "14:43:49",
    "page_number": "",
    "line_number": "",
    "description": "No change detected",
    "lines_added_count": 0,
    "lines_removed_count": 0,
    "lines_added_text": "",
    "lines_removed_text": ""
  },
  {
    "document": "chapter3.txt",
    "version_change": "chapter3_0 to chapter3_1",
    "status": "unchanged",
    "changed_date": "2025-11-07",
    "changed_time": "11:31:05",
    "page_number": "",
    "line_number": "",
    "description": "No change detected",
    "lines_added_count": 0,
    "lines_removed_count": 0,
    "lines_added_text": "",
    "lines_removed_text": ""
  },
  {
    "document": "chapter3.txt",
    "version_change": "chapter3_1 to chapter3_2",
    "status": "changed",
    "changed_date": "2025-11-07",
    "changed_time": "15:46:31",
    "page_number": 1,
    "line_number": 9,
    "description": "Word changed",
    "lines_added_count": 1,
    "lines_removed_count": 1,
    "lines_added_text": "One mirror stood broken, its fragments dark and lifeless.",
    "lines_removed_text": "One mirror stood shattered, its fragments dark and lifeless."
  },
  {
    "document": "chapter3.txt",
    "version_change": "chapter3_1 to chapter3_2",
    "status": "changed",
    "changed_date": "2025-11-07",
    "changed_time": "15:46:31",
    "page_number": 1,
    "line_number": 13,
    "description": "Word changed",
    "lines_added_count": 1,
    "lines_removed_count": 1,
    "lines_added_text": "Leron stepped back, eyes wide open.",
    "lines_removed_text": "Leron stepped back, eyes wide."
  }
]